AUTHORS.rst
CONTRIBUTING.rst
HISTORY.rst
LICENSE
MANIFEST.in
README.rst
setup.cfg
setup.py
docs/Makefile
docs/authors.rst
docs/conf.py
docs/contributing.rst
docs/history.rst
docs/index.rst
docs/installation.rst
docs/make.bat
docs/readme.rst
docs/tutorial.rst
docs/usage.rst
docs/releases/v0.1.0.rst
modish/__init__.py
modish/estimator.py
modish/model.py
modish/modish.py
modish.egg-info/PKG-INFO
modish.egg-info/SOURCES.txt
modish.egg-info/dependency_links.txt
modish.egg-info/not-zip-safe
modish.egg-info/pbr.json
modish.egg-info/top_level.txt